{
    "정훈" : {
        "PA": 26,
        "ePA": 25,
        "AB": 22,
        "R": 3,
        "H": 3,
        "2B": 2,
        "3B": 0,
        "HR": 0,
        "TB": 5,
        "RBI": 0,
        "BB": 4,
        "HP": 0,
        "IB": 1,
        "SO": 6,
        "GDP": 1,
        "SH": 0,
        "SF": 0,
        "AVG": 0.136,
        "OBP": 0.269,
        "SLG": 0.227,
        "OPS": 0.496,
        "NP": 110,
        "avLI": 1.19,
        "RE24": -4.55,
        "WPA": -0.284
    },

    "박승욱" : {
        "PA": 12,
        "ePA": 12,
        "AB": 11,
        "R": 4,
        "H": 4,
        "2B": 1,
        "3B": 0,
        "HR": 2,
        "TB": 11,
        "RBI": 4,
        "BB": 1,
        "HP": 0,
        "IB": 0,
        "SO": 3,
        "GDP": 0,
        "SH": 0,
        "SF": 0,
        "AVG": 0.364,
        "OBP": 0.417,
        "SLG": 1.000,
        "OPS": 1.417,
        "NP": 57,
        "avLI": 0.97,
        "RE24": 2.88,
        "WPA": 0.470
    },
    "정보근" : {
        "PA": 6,
        "ePA": 5,
        "AB": 5,
        "R": 0,
        "H": 1,
        "2B": 0,
        "3B": 0,
        "HR": 0,
        "TB": 1,
        "RBI": 0,
        "BB": 0,
        "HP": 0,
        "IB": 0,
        "SO": 0,
        "GDP": 0,
        "SH": 0,
        "SF": 1,
        "AVG": 0.200,
        "OBP": 0.200,
        "SLG": 0.200,
        "OPS": 0.400,
        "NP": 19,
        "avLI": 1.27,
        "RE24": -0.77,
        "WPA": -0.087
    }
}